{
  "profiles": [
    {
      "name": "epi-a – conservative",
      "ticker": "epi-a",
      "params": {
        "use_rsi_filter": true,
        "rsi_window": 8,
        "rsi_min": 15.910745556492394,
        "rsi_max": 66.567760838976,
        "use_trend_filter": false,
        "trend_ma_type": "SMA",
        "trend_ma_window": 165,
        "breakout_lookback": 44,
        "exit_lookback": 20,
        "use_macd_filter": false,
        "macd_fast": 13,
        "macd_slow": 21,
        "macd_signal": 9,
        "use_bb_filter": false,
        "bb_window": 30,
        "bb_nstd": 1.7041428206749791,
        "bb_min": 0.16560641080560715,
        "use_stop_loss": false,
        "stop_mode": "atr",
        "stop_loss_pct": 0.1340843777081214,
        "atr_window": 16,
        "atr_mult": 1.8720833798985523,
        "use_atr_trailing": true,
        "atr_trail_mult": 3.2149142753513953,
        "from_date": "2020-10-04",
        "to_date": "2025-10-05"
      },
      "metrics": {
        "Bars": 1259,
        "Trades": 46,
        "TotalReturn": 1.4886479620845359,
        "MaxDD": -0.11795153619105636,
        "SharpeD": 1.4009771404643254,
        "BuyHold": 0.5847619047619048,
        "FinalEquity": 248864.7962084536,
        "CAGR": 0.2003015908542909
      }
    },
    {
      "name": "epi-a – balanced",
      "ticker": "epi-a",
      "params": {
        "use_rsi_filter": true,
        "rsi_window": 12,
        "rsi_min": 33.83902222405665,
        "rsi_max": 69.82362180163,
        "use_trend_filter": false,
        "trend_ma_type": "EMA",
        "trend_ma_window": 187,
        "breakout_lookback": 79,
        "exit_lookback": 37,
        "use_macd_filter": false,
        "macd_fast": 9,
        "macd_slow": 19,
        "macd_signal": 9,
        "use_bb_filter": false,
        "bb_window": 26,
        "bb_nstd": 2.3584597322679217,
        "bb_min": 0.23333091575076167,
        "use_stop_loss": true,
        "stop_mode": "pct",
        "stop_loss_pct": 0.06489867028116456,
        "atr_window": 10,
        "atr_mult": 2.792965364670957,
        "use_atr_trailing": true,
        "atr_trail_mult": 2.4489930629641616,
        "from_date": "2020-10-04",
        "to_date": "2025-10-05"
      },
      "metrics": {
        "Bars": 1259,
        "Trades": 51,
        "TotalReturn": 1.5254823690136163,
        "MaxDD": -0.21155933446507225,
        "SharpeD": 1.048914239128867,
        "BuyHold": 0.5847619047619048,
        "FinalEquity": 252548.2369013616,
        "CAGR": 0.2038382293922647
      }
    },
    {
      "name": "epi-a – aggressive",
      "ticker": "epi-a",
      "params": {
        "use_rsi_filter": true,
        "rsi_window": 13,
        "rsi_min": 34.49156207637925,
        "rsi_max": 77.23892191076919,
        "use_trend_filter": false,
        "trend_ma_type": "SMA",
        "trend_ma_window": 119,
        "breakout_lookback": 38,
        "exit_lookback": 47,
        "use_macd_filter": true,
        "macd_fast": 8,
        "macd_slow": 23,
        "macd_signal": 8,
        "use_bb_filter": true,
        "bb_window": 19,
        "bb_nstd": 2.085376960338426,
        "bb_min": 0.5508299881755352,
        "use_stop_loss": false,
        "stop_mode": "pct",
        "stop_loss_pct": 0.1551652324501255,
        "atr_window": 19,
        "atr_mult": 2.987418904975468,
        "use_atr_trailing": false,
        "atr_trail_mult": 1.8913511681448987,
        "from_date": "2020-10-04",
        "to_date": "2025-10-05"
      },
      "metrics": {
        "Bars": 1259,
        "Trades": 16,
        "TotalReturn": 1.3699214858067692,
        "MaxDD": -0.16939104029599916,
        "SharpeD": 1.217349520977403,
        "BuyHold": 0.5847619047619048,
        "FinalEquity": 236992.1485806769,
        "CAGR": 0.18860962432412198
      }
    }
  ]
}